serializer_lib/__init__.py
serializer_lib/factory/__init__.py
serializer_lib/factory/factory.py
serializer_lib/factory/parsers/__init__.py
serializer_lib/factory/parsers/constans.py
serializer_lib/factory/parsers/parser.py
serializer_lib/factory/parsers/json/ParserJson.py
serializer_lib/factory/parsers/json/__init__.py
serializer_lib/factory/parsers/json/constans.py
serializer_lib/factory/parsers/json/functions.py
serializer_lib/factory/parsers/toml/ParserToml.py
serializer_lib/factory/parsers/toml/__init__.py
serializer_lib/factory/parsers/yaml/ParserYaml.py
serializer_lib/factory/parsers/yaml/__init__.py
serializer_lib/serialization/__init__.py
serializer_lib/serialization/constants.py
serializer_lib/serialization/serializer.py
xotab_serialization-0.1.0.dist-info/METADATA
xotab_serialization-0.1.0.dist-info/WHEEL
xotab_serialization-0.1.0.dist-info/top_level.txt
xotab_serialization-0.1.0.dist-info/RECORD
